README.rst
setup.cfg
setup.py
brainrise/__init__.py
brainrise/core.py
brainrise/datasets.py
brainrise/hist.py
brainrise/info.py
brainrise/intensity.py
brainrise/spatial.py
brainrise/transform.py
brainrise/utils.py
brainrise.egg-info/PKG-INFO
brainrise.egg-info/SOURCES.txt
brainrise.egg-info/dependency_links.txt
brainrise.egg-info/requires.txt
brainrise.egg-info/top_level.txt
brainrise/tests/test_augmentation.py