Metadata-Version: 1.1
Name: brainrise
Version: 0.0.0
Summary: 
